LICENSE.txt
MANIFEST.in
README.rst
setup.cfg
setup.py
proxy_manager.egg-info/PKG-INFO
proxy_manager.egg-info/SOURCES.txt
proxy_manager.egg-info/dependency_links.txt
proxy_manager.egg-info/top_level.txt
proxymngr/__init__.py
proxymngr/manager.py