Metadata-Version: 1.1
Name: proxy-manager
Version: 0.0.5
Summary: Proxy Manager
Home-page: https://github.com/kfichter/proxy-manager
Author: Kelvin Fichter
Author-email: UNKNOWN
License: MIT
Keywords: proxy management development
Platform: UNKNOWN
Classifier: Development Status :: 3 - Alpha
Classifier: Intended Audience :: Developers
Classifier: Topic :: Software Development :: Libraries :: Python Modules
Classifier: License :: OSI Approved :: MIT License
Classifier: Programming Language :: Python :: 3.5
